zonda_rotgrid/__init__.py
zonda_rotgrid/cli.py
zonda_rotgrid/core.py
zonda_rotgrid-0.4.1.dist-info/licenses/LICENSE
zonda_rotgrid-0.4.1.dist-info/METADATA
zonda_rotgrid-0.4.1.dist-info/WHEEL
zonda_rotgrid-0.4.1.dist-info/entry_points.txt
zonda_rotgrid-0.4.1.dist-info/top_level.txt
zonda_rotgrid-0.4.1.dist-info/RECORD
