Metadata-Version: 2.4
Name: zonda_rotgrid
Version: 0.4.1
Summary: Generate regular or rotated coordinate grid NetCDF files for weather and climate models.
Author: C2SM
License: MIT
Requires-Python: >=3.7
License-File: LICENSE
Requires-Dist: numpy
Requires-Dist: xarray
Requires-Dist: pyproj
Requires-Dist: netCDF4
Requires-Dist: h5netcdf
Requires-Dist: scipy
Dynamic: author
Dynamic: description
Dynamic: description-content-type
Dynamic: license
Dynamic: license-file
Dynamic: requires-dist
Dynamic: requires-python
Dynamic: summary
